gpt_cli/__init__.py
gpt_cli/__main__.py
demon_gptcli-0.1.2.dist-info/LICENSE
demon_gptcli-0.1.2.dist-info/METADATA
demon_gptcli-0.1.2.dist-info/WHEEL
demon_gptcli-0.1.2.dist-info/entry_points.txt
demon_gptcli-0.1.2.dist-info/RECORD
